loregen_common/__init__.py
loregen_common/models.py
loregen_common/openrouter.py
loregen_common/utils.py
loregen_common-0.1.3.dist-info/METADATA
loregen_common-0.1.3.dist-info/WHEEL
loregen_common-0.1.3.dist-info/RECORD
